[{"__symbolic":"module","version":3,"metadata":{"FilesModule":{"__symbolic":"class","decorators":[{"__symbolic":"call","expression":{"__symbolic":"reference","module":"@angular/core","name":"NgModule"},"arguments":[{"entryComponents":[{"__symbolic":"reference","module":"./asset-list/asset-list.component","name":"AssetListComponent"},{"__symbolic":"reference","module":"./asset-select/asset-select.component","name":"AssetSelectComponent"},{"__symbolic":"reference","module":"./asset-input/asset-input.component","name":"AssetInputComponent"},{"__symbolic":"reference","module":"./upload/upload.component","name":"UploadComponent"}],"declarations":[{"__symbolic":"reference","module":"./asset-list/asset-list.component","name":"AssetListComponent"},{"__symbolic":"reference","module":"./asset-select/asset-select.component","name":"AssetSelectComponent"},{"__symbolic":"reference","module":"./asset-input/asset-input.component","name":"AssetInputComponent"},{"__symbolic":"reference","module":"./upload/upload.component","name":"UploadComponent"}],"imports":[{"__symbolic":"reference","module":"@angular/common","name":"CommonModule"},{"__symbolic":"reference","module":"@angular/forms","name":"FormsModule"},{"__symbolic":"reference","module":"@ec.components/ui/src/ui.module","name":"UiModule"},{"__symbolic":"reference","module":"../sdk/sdk.module","name":"SdkModule"}],"exports":[{"__symbolic":"reference","module":"./asset-list/asset-list.component","name":"AssetListComponent"},{"__symbolic":"reference","module":"./asset-select/asset-select.component","name":"AssetSelectComponent"},{"__symbolic":"reference","module":"./asset-input/asset-input.component","name":"AssetInputComponent"},{"__symbolic":"reference","module":"./upload/upload.component","name":"UploadComponent"},{"__symbolic":"reference","module":"../sdk/sdk.module","name":"SdkModule"}],"providers":[{"__symbolic":"reference","module":"./file.service","name":"FileService"}]}]}]}}},{"__symbolic":"module","version":1,"metadata":{"FilesModule":{"__symbolic":"class","decorators":[{"__symbolic":"call","expression":{"__symbolic":"reference","module":"@angular/core","name":"NgModule"},"arguments":[{"entryComponents":[{"__symbolic":"reference","module":"./asset-list/asset-list.component","name":"AssetListComponent"},{"__symbolic":"reference","module":"./asset-select/asset-select.component","name":"AssetSelectComponent"},{"__symbolic":"reference","module":"./asset-input/asset-input.component","name":"AssetInputComponent"},{"__symbolic":"reference","module":"./upload/upload.component","name":"UploadComponent"}],"declarations":[{"__symbolic":"reference","module":"./asset-list/asset-list.component","name":"AssetListComponent"},{"__symbolic":"reference","module":"./asset-select/asset-select.component","name":"AssetSelectComponent"},{"__symbolic":"reference","module":"./asset-input/asset-input.component","name":"AssetInputComponent"},{"__symbolic":"reference","module":"./upload/upload.component","name":"UploadComponent"}],"imports":[{"__symbolic":"reference","module":"@angular/common","name":"CommonModule"},{"__symbolic":"reference","module":"@angular/forms","name":"FormsModule"},{"__symbolic":"reference","module":"@ec.components/ui/src/ui.module","name":"UiModule"},{"__symbolic":"reference","module":"../sdk/sdk.module","name":"SdkModule"}],"exports":[{"__symbolic":"reference","module":"./asset-list/asset-list.component","name":"AssetListComponent"},{"__symbolic":"reference","module":"./asset-select/asset-select.component","name":"AssetSelectComponent"},{"__symbolic":"reference","module":"./asset-input/asset-input.component","name":"AssetInputComponent"},{"__symbolic":"reference","module":"./upload/upload.component","name":"UploadComponent"},{"__symbolic":"reference","module":"../sdk/sdk.module","name":"SdkModule"}],"providers":[{"__symbolic":"reference","module":"./file.service","name":"FileService"}]}]}]}}}]