{
  "id": "core-concepts/form-options",
  "title": "Form API",
  "sidebar_label": "Form API",
  "description": "This document shows which config options can be used to control forms.",
  "source": "/Users/felix/entrecode/ec.components/website/docs/core-concepts/form-options.mdx",
  "permalink": "/docs/core-concepts/form-options",
  "sidebar": "docs",
  "category": "Guided Tour",
  "next": "core-concepts/items",
  "previous": "core-concepts/list-options",
  "previous_title": "List API",
  "next_title": "Items"
}