[{"__symbolic":"module","version":3,"metadata":{"DefaultEntryInputComponent":{"__symbolic":"class","extends":{"__symbolic":"reference","module":"@ec.components/ui/src/form/default-input/default-input.component","name":"DefaultInputComponent"},"decorators":[{"__symbolic":"call","expression":{"__symbolic":"reference","module":"@angular/core","name":"Component"},"arguments":[{"templateUrl":"./default-entry-input.component.html"}]}]}}},{"__symbolic":"module","version":1,"metadata":{"DefaultEntryInputComponent":{"__symbolic":"class","extends":{"__symbolic":"reference","module":"@ec.components/ui/src/form/default-input/default-input.component","name":"DefaultInputComponent"},"decorators":[{"__symbolic":"call","expression":{"__symbolic":"reference","module":"@angular/core","name":"Component"},"arguments":[{"templateUrl":"./default-entry-input.component.html"}]}]}}}]